pypi_show_urls
