Metadata-Version: 1.0
Name: pypi-show-urls
Version: 2.1.1
Summary: Shows all the installation candidates for a list of packages
Home-page: https://github.com/dstufft/pypi-show-urls
Author: Donald Stufft
Author-email: donald@stufft.io
License: UNKNOWN
Platform: UNKNOWN
